pubmed_cited_by/__init__.py
pubmed_cited_by/bin.py
pubmed_cited_by/core.py
pubmed_cited_by/utils.py
pubmed_cited_by/version.json
pubmed_cited_by-1.0.0.dist-info/METADATA
pubmed_cited_by-1.0.0.dist-info/WHEEL
pubmed_cited_by-1.0.0.dist-info/entry_points.txt
pubmed_cited_by-1.0.0.dist-info/top_level.txt
pubmed_cited_by-1.0.0.dist-info/RECORD
